{
    "Case ID": "086473",
    "Crime_Name": [
        "Judicial Review of Refugee Status Decision"
    ],
    "Crime_Type": [
        "Violations of Immigration Regulations"
    ],
    "Violation_Type": [
        "Procedural violation in decision-making"
    ],
    "Legal_Issue": [
        "Adequacy of written reasons in refugee status determination"
    ],
    "Governing_Law": [
        "Immigration and Refugee Protection Act, sections 169(d), (e), (f)"
    ],
    "Application_Facts": [
        "IRB granted refugee status to Ange Mokono but failed to address key arguments, including exclusion under Article 1F(a)"
    ],
    "Decision_Outcome": [
        "Original decision found inadequate; case remanded for reconsideration"
    ],
    "Remedy_Requested": [
        "Judicial review of IRB decision"
    ],
    "Court_Ruling": [
        "Judicial review granted"
    ],
    "Claimant_Status": [
        "Minister of Immigration"
    ],
    "Defendant_Behavior": [
        "IRB issued incomplete and unintelligible reasons"
    ],
    "Grounds_for_Claim": [
        "Failure to provide adequate reasons, breach of procedural fairness"
    ],
    "Legal_Standard": [
        "Clear, precise, and intelligible written reasons required under Rule 61(3) of the Refugee Protection Division Rules"
    ],
    "Assessment_Factor": [
        "Presence or absence of analysis on exclusion clauses"
    ],
    "Applicable_Legislation": [
        "Immigration and Refugee Protection Act, Refugee Protection Division Rules"
    ],
    "Procedural_Issue": [
        "Insufficient reasoning affecting fairness of process"
    ],
    "Review_Standard": [
        "Reasonableness"
    ],
    "Credibility_Assessment": [],
    "Evidence_Used": [],
    "Legal_Provision_Cited": [
        "Section 169(d), (e), (f), Rule 61(3)"
    ],
    "Application_Basis": [
        "Failure to address Minister's argument under Article 1F(a)"
    ],
    "Evidence_Assessed": [],
    "Relief_Sought": [
        "Remittal of decision for reconsideration by a differently constituted panel"
    ],
    "Governing_Rule": [
        "Rule 61(3) of the Refugee Protection Division Rules"
    ],
    "Evidentiary_Deficiency": [
        "Lack of clarity and completeness in written reasons"
    ],
    "Outcome": [
        "Case remanded for reconsideration"
    ],
    "Decisional_Body": [
        "Immigration and Refugee Board (IRB)"
    ],
    "Harm_Assessment": [
        "Risk of unfair determination due to inadequate reasoning"
    ],
    "Cause_Description": [
        "Ange Mokono was granted refugee status without sufficient written justification, particularly regarding potential exclusion under Article 1F(a)"
    ],
    "Evidence_Handling": [
        "Failure to properly document assessment of evidence and arguments"
    ],
    "Legal_Provision_Violated": [
        "Sections 169(d), (e), (f), Rule 61(3)"
    ],
    "Evidence_Issues": [
        "Incomplete and unintelligible reasons"
    ],
    "Residency_Compliance": [],
    "Misrepresentation_Element": [],
    "Legal_Provision": [
        "Immigration and Refugee Protection Act, Refugee Protection Division Rules"
    ],
    "Jurisdictional_Issue": [],
    "Evidence_Assessment": [],
    "Decision_Rationale": [
        "Written reasons must enable understanding of how decision was reached, especially when exclusion clauses are at issue"
    ],
    "Country_of_Origin": [],
    "Decision_Making_Body": [
        "Immigration and Refugee Board (IRB)"
    ],
    "Evidentiary_Issues": [
        "Failure to address key evidence and legal arguments in writing"
    ],
    "Legal_Standard_Applied": [
        "Requirement for clear, precise, and intelligible reasons in administrative decisions"
    ]
}