{
    "Case ID": "089989",
    "Crime_Name": [
        "Patent Infringement Dispute"
    ],
    "Crime_Type": [
        "Property Crimes"
    ],
    "Dispute_Type": [
        "Patent Infringement"
    ],
    "Legal_Issue": [
        "Scope of permissible discovery questions"
    ],
    "Governing_Law": [
        "Rules governing discovery and prior case law"
    ],
    "Procedural_Stage": [
        "Discovery phase"
    ],
    "Evidence_Assessment": [
        "Relevance and timing of discovery questions"
    ],
    "Decision_Outcome": [
        "Defendant not required to answer post-1990 market research or patent validity questions; follow-up questions on prior art and sales allowed"
    ],
    "Burden_of_Proof": [
        "Plaintiff bears burden to show relevance of discovery requests"
    ],
    "Credibility_Factor": [],
    "Legal_Rule": [
        "Relevant discovery questions must advance a party's case or damage the opponent's; irrelevant or expert opinion-seeking questions are disallowed"
    ],
    "Standard_of_Review": [],
    "Procedural_Issue": [
        "Permissibility and scope of discovery"
    ],
    "Grounds_for_Claim": [
        "Alleged patent infringement"
    ],
    "Outcome_on_Merits": [
        "Not reached; decision limited to discovery disputes"
    ],
    "Decision_Maker": [
        "Court"
    ],
    "Judicial_Review_Outcome": [],
    "Review_Standard": [],
    "Procedural_Fairness_Assessment": [
        "Court applied discovery rules fairly based on relevance and timing"
    ],
    "Key_Evidence_Considered": [
        "Market research (post-1990), prior art, sales data, patent validity inquiries"
    ],
    "Legal_Framework": [
        "Federal rules of civil procedure regarding discovery"
    ],
    "Applicant_Challenge": [
        "Plaintiff's attempt to compel answers to broad discovery questions"
    ],
    "Court_Result": [
        "Limited grant of oral discovery; costs awarded proportionally"
    ],
    "Legal_Rule_Source": [
        "Prior case law and procedural rules"
    ],
    "Standard_of_Proof": [
        "Relevance under civil discovery standards"
    ],
    "Defendant_Response": [
        "Refused to answer certain discovery questions as irrelevant"
    ],
    "Evidence_Type": [
        "Documentary evidence, discovery responses"
    ],
    "Remedy_Requested": [
        "Compel defendant to answer discovery questions"
    ],
    "Outcome": [
        "Partially granted: follow-up questions allowed, others denied"
    ],
    "Decision_Authority": [
        "Presiding court"
    ],
    "Remedy_Sought": [
        "Oral discovery and cost allocation"
    ],
    "Resolution_Mechanism": [
        "Court ruling on discovery motions"
    ],
    "Legal_Provision": [
        "Discovery rules in civil litigation"
    ],
    "Authority": [
        "Court with jurisdiction over patent disputes"
    ],
    "Claimant_Status": [
        "Plaintiff in patent infringement suit"
    ],
    "Legal_Provision_Cited": [
        "Rules governing discovery"
    ],
    "Grounds_for_Inadmissibility_or_Allegation": [
        "Irrelevance, redundancy, timing (post-patent application)"
    ],
    "Applicable_Process": [
        "Pre-trial discovery process"
    ],
    "Outcome_of_Review": [],
    "Pending_Relief_or_Application": [
        "Motion to compel discovery"
    ],
    "Jurisdiction": [
        "Federal court (implied by patent subject matter)"
    ],
    "Governing_Rule": [
        "Relevance and timing standards for discovery"
    ]
}