{
    "Case ID": "025490",
    "Different Crime": [
        {
            "Crime Name": "Discrimination complaint under Canadian Human Rights Act",
            "Crime Type": "Human_Rights_or_International_Law_Violations",
            "time_limit": [
                "one-year limitation period under s. 41(e)"
            ],
            "administrative_error": [
                "no prejudice or error in exercising discretion"
            ],
            "judicial_review_process": [
                "court reviewed CHRC's discretion and evidence of prejudice"
            ],
            "burden_of_proof": [
                "CHRC properly exercised its discretion"
            ],
            "decision_outcome": [
                "Court upheld CHRC's decision to investigate"
            ],
            "charter_rights_violation": [],
            "humanitarian_and_compassionate_grounds": [],
            "compelling_reasons": [],
            "procedural_fairness": [],
            "credibility_findings": [],
            "risk_analysis": [],
            "state_protection": [],
            "human_rights_violations": [],
            "immigration_status": [],
            "refugee_definition": [],
            "discrimination_grounds": [
                "perceived disability"
            ],
            "senior_official_involvement": [],
            "war_crimes_complicity": [],
            "internal_flight_alternative": [],
            "evidentiary_standard": [],
            "reasonableness_of_decision": [
                "CHRC's decision found reasonable"
            ],
            "new_evidence_impact": [],
            "specific_legal_test_application": [],
            "national_security_concerns": [],
            "persecution_grounds": [],
            "immigration_policy": [],
            "membership_in_persecutory_group": [],
            "legal_basis": [
                "Canadian Human Rights Act, s. 41(e)"
            ]
        }
    ]
}