{
    "Case ID": "034352",
    "Different Crime": [
        {
            "Crime Name": "Refugee Claim Dismissal",
            "Crime Type": "Refugee_Claim-related_Issues",
            "state_protection_analysis": [
                "St. Vincent's political and judicial institutions were capable of protecting him"
            ],
            "reasonableness_standard": [
                "Board's decision was reasonable"
            ],
            "risk_of_persecution": [
                "fear of persecution by ULP supporters in St. Vincent"
            ],
            "decision_outcome": [
                "application for judicial review is dismissed"
            ],
            "review_standard": [
                "Federal Court reviewed the Board's decision on state protection adequacy"
            ]
        }
    ]
}